{"plot": "/static\\top_subcategories_by_profit.png", "city_subcategory": [{"City": "Bodi", "Sub Category": "Soft Drinks", "Sales": 43225, "Profit": 11083.22, "Frequency": 31}, {"City": "Bodi", "Sub Category": "Health Drinks", "Sales": 45948, "Profit": 10897.24, "Frequency": 31}, {"City": "Bodi", "Sub Category": "Breads & Buns", "Sales": 34837, "Profit": 9928.68, "Frequency": 23}, {"City": "Chennai", "Sub Category": "Health Drinks", "Sales": 55662, "Profit": 14951.1, "Frequency": 39}, {"City": "Chennai", "Sub Category": "Soft Drinks", "Sales": 45582, "Profit": 11656.28, "Frequency": 29}, {"City": "Chennai", "Sub Category": "Masalas", "Sales": 40425, "Profit": 11305.43, "Frequency": 26}, {"City": "Coimbatore", "Sub Category": "Health Drinks", "Sales": 52277, "Profit": 13520.79, "Frequency": 32}, {"City": "Coimbatore", "Sub Category": "Soft Drinks", "Sales": 45815, "Profit": 11967.26, "Frequency": 29}, {"City": "Coimbatore", "Sub Category": "Chocolates", "Sales": 35973, "Profit": 9854.64, "Frequency": 22}, {"City": "Cumbum", "Sub Category": "Soft Drinks", "Sales": 42389, "Profit": 10639.119999999999, "Frequency": 28}, {"City": "Cumbum", "Sub Category": "Breads & Buns", "Sales": 34488, "Profit": 10257.02, "Frequency": 22}, {"City": "Cumbum", "Sub Category": "Fish", "Sales": 34828, "Profit": 10209.19, "Frequency": 24}, {"City": "Dharmapuri", "Sub Category": "Cookies", "Sales": 46097, "Profit": 11998.55, "Frequency": 28}, {"City": "Dharmapuri", "Sub Category": "Edible Oil & Ghee", "Sales": 33170, "Profit": 8621.01, "Frequency": 24}, {"City": "Dharmapuri", "Sub Category": "Cakes", "Sales": 34467, "Profit": 8494.82, "Frequency": 25}, {"City": "Dindigul", "Sub Category": "Biscuits", "Sales": 37678, "Profit": 10634.53, "Frequency": 26}, {"City": "Dindigul", "Sub Category": "Soft Drinks", "Sales": 40882, "Profit": 9573.41, "Frequency": 28}, {"City": "Dindigul", "Sub Category": "Health Drinks", "Sales": 32253, "Profit": 9163.68, "Frequency": 25}, {"City": "Kanyakumari", "Sub Category": "Health Drinks", "Sales": 45237, "Profit": 11803.91, "Frequency": 30}, {"City": "Kanyakumari", "Sub Category": "Spices", "Sales": 42392, "Profit": 10893.34, "Frequency": 26}, {"City": "Kanyakumari", "Sub Category": "Mutton", "Sales": 37743, "Profit": 10371.87, "Frequency": 26}, {"City": "Karur", "Sub Category": "Soft Drinks", "Sales": 44164, "Profit": 11702.32, "Frequency": 30}, {"City": "Karur", "Sub Category": "Breads & Buns", "Sales": 42065, "Profit": 11536.08, "Frequency": 29}, {"City": "Karur", "Sub Category": "Cookies", "Sales": 35295, "Profit": 9835.96, "Frequency": 22}, {"City": "Krishnagiri", "Sub Category": "Biscuits", "Sales": 41992, "Profit": 11341.96, "Frequency": 26}, {"City": "Krishnagiri", "Sub Category": "Noodles", "Sales": 36359, "Profit": 10138.4, "Frequency": 26}, {"City": "Krishnagiri", "Sub Category": "Soft Drinks", "Sales": 37833, "Profit": 9866.78, "Frequency": 26}, {"City": "Madurai", "Sub Category": "Soft Drinks", "Sales": 59258, "Profit": 14447.46, "Frequency": 38}, {"City": "Madurai", "Sub Category": "Health Drinks", "Sales": 51903, "Profit": 13501.33, "Frequency": 32}, {"City": "Madurai", "Sub Category": "Masalas", "Sales": 38982, "Profit": 10107.4, "Frequency": 26}, {"City": "Nagercoil", "Sub Category": "Cakes", "Sales": 39645, "Profit": 10175.83, "Frequency": 25}, {"City": "Nagercoil", "Sub Category": "Organic Vegetables", "Sales": 33570, "Profit": 9055.61, "Frequency": 24}, {"City": "Nagercoil", "Sub Category": "Health Drinks", "Sales": 31706, "Profit": 9052.86, "Frequency": 21}, {"City": "Namakkal", "Sub Category": "Soft Drinks", "Sales": 50094, "Profit": 13565.66, "Frequency": 31}, {"City": "Namakkal", "Sub Category": "Breads & Buns", "Sales": 35383, "Profit": 9426.85, "Frequency": 24}, {"City": "Namakkal", "Sub Category": "Health Drinks", "Sales": 39156, "Profit": 8518.2, "Frequency": 24}, {"City": "Ooty", "Sub Category": "Health Drinks", "Sales": 54995, "Profit": 12316.03, "Frequency": 38}, {"City": "Ooty", "Sub Category": "Organic Staples", "Sales": 36346, "Profit": 10431.35, "Frequency": 22}, {"City": "Ooty", "Sub Category": "Soft Drinks", "Sales": 35421, "Profit": 9017.22, "Frequency": 24}, {"City": "Perambalur", "Sub Category": "Soft Drinks", "Sales": 69535, "Profit": 16840.46, "Frequency": 44}, {"City": "Perambalur", "Sub Category": "Noodles", "Sales": 40737, "Profit": 11006.4, "Frequency": 25}, {"City": "Perambalur", "Sub Category": "Health Drinks", "Sales": 38813, "Profit": 10375.79, "Frequency": 28}, {"City": "Pudukottai", "Sub Category": "Noodles", "Sales": 38017, "Profit": 11253.3, "Frequency": 23}, {"City": "Pudukottai", "Sub Category": "Health Drinks", "Sales": 46449, "Profit": 11163.529999999999, "Frequency": 31}, {"City": "Pudukottai", "Sub Category": "Soft Drinks", "Sales": 38923, "Profit": 9858.27, "Frequency": 27}, {"City": "Ramanadhapuram", "Sub Category": "Health Drinks", "Sales": 64172, "Profit": 14286.74, "Frequency": 40}, {"City": "Ramanadhapuram", "Sub Category": "Soft Drinks", "Sales": 41031, "Profit": 11422.75, "Frequency": 23}, {"City": "Ramanadhapuram", "Sub Category": "Cookies", "Sales": 38070, "Profit": 10489.0, "Frequency": 24}, {"City": "Salem", "Sub Category": "Edible Oil & Ghee", "Sales": 36490, "Profit": 10262.64, "Frequency": 23}, {"City": "Salem", "Sub Category": "Soft Drinks", "Sales": 40921, "Profit": 9938.96, "Frequency": 27}, {"City": "Salem", "Sub Category": "Noodles", "Sales": 38110, "Profit": 9789.98, "Frequency": 24}, {"City": "Tenkasi", "Sub Category": "Health Drinks", "Sales": 52693, "Profit": 14226.99, "Frequency": 36}, {"City": "Tenkasi", "Sub Category": "Cookies", "Sales": 44241, "Profit": 12069.2, "Frequency": 27}, {"City": "Tenkasi", "Sub Category": "Fish", "Sales": 38668, "Profit": 9886.119999999999, "Frequency": 22}, {"City": "Theni", "Sub Category": "Soft Drinks", "Sales": 49339, "Profit": 12853.38, "Frequency": 33}, {"City": "Theni", "Sub Category": "Breads & Buns", "Sales": 32859, "Profit": 8632.15, "Frequency": 19}, {"City": "Theni", "Sub Category": "Fish", "Sales": 29019, "Profit": 8130.53, "Frequency": 21}, {"City": "Tirunelveli", "Sub Category": "Soft Drinks", "Sales": 55821, "Profit": 13785.69, "Frequency": 38}, {"City": "Tirunelveli", "Sub Category": "Health Drinks", "Sales": 45244, "Profit": 12425.93, "Frequency": 33}, {"City": "Tirunelveli", "Sub Category": "Cookies", "Sales": 42191, "Profit": 11054.44, "Frequency": 29}, {"City": "Trichy", "Sub Category": "Soft Drinks", "Sales": 43524, "Profit": 11083.7, "Frequency": 27}, {"City": "Trichy", "Sub Category": "Chocolates", "Sales": 37907, "Profit": 10896.49, "Frequency": 25}, {"City": "Trichy", "Sub Category": "Mutton", "Sales": 34759, "Profit": 9163.62, "Frequency": 21}, {"City": "Vellore", "Sub Category": "Health Drinks", "Sales": 54498, "Profit": 16319.8, "Frequency": 35}, {"City": "Vellore", "Sub Category": "Chocolates", "Sales": 44054, "Profit": 12333.789999999999, "Frequency": 27}, {"City": "Vellore", "Sub Category": "Soft Drinks", "Sales": 44676, "Profit": 10713.11, "Frequency": 29}, {"City": "Viluppuram", "Sub Category": "Health Drinks", "Sales": 52584, "Profit": 12840.6, "Frequency": 37}, {"City": "Viluppuram", "Sub Category": "Chocolates", "Sales": 36882, "Profit": 10206.36, "Frequency": 27}, {"City": "Viluppuram", "Sub Category": "Edible Oil & Ghee", "Sales": 33263, "Profit": 10201.27, "Frequency": 22}, {"City": "Virudhunagar", "Sub Category": "Health Drinks", "Sales": 44988, "Profit": 11982.68, "Frequency": 28}, {"City": "Virudhunagar", "Sub Category": "Noodles", "Sales": 41024, "Profit": 11340.09, "Frequency": 26}, {"City": "Virudhunagar", "Sub Category": "Fresh Fruits", "Sales": 35012, "Profit": 9136.9, "Frequency": 24}]}